example/front-end/test_design.v
//// 4-Bit counter

module test_design(
    input clk,
    input rst,
    output reg [3:0]count
);

    reg [3:0]count_nxt;

    //////////// Flops
    always@(posedge clk) 
        begin : FLOPS
            if(rst)
                count <= 4'b0000;
            else
                count <= count_nxt;
        end

    /////////// Datapath
    always@(*)
        begin : Combinational
                count_nxt = count + 1;
        end


endmodule

example/front-end/RTL/testbench/test_design_tb.v
`timescale 1ns/1ps

module test_design_tb;

    reg clk,rst;
    wire [3:0]count;

    test_design dut(
        .clk(clk),
        .rst(rst),
        .count(count)
    );

    always #5 clk = ~clk;

    initial begin
        clk = 0;
        rst = 1;

        #12;
        rst = 0;


        #60;
        $finish;

    end

    initial begin
        $dumpfile("sim.vcd");
        $dumpvars(0,test_design_tb);

    end



endmodule

example/front-end/RTL/testbench/sim.vcd
$date
	Wed Sep 24 02:26:25 2025
$end
$version
	Icarus Verilog
$end
$timescale
	1ps
$end
$scope module test_design_tb $end
$var wire 4 ! count [3:0] $end
$var reg 1 " clk $end
$var reg 1 # rst $end
$scope module dut $end
$var wire 1 " clk $end
$var wire 1 # rst $end
$var reg 4 $ count [3:0] $end
$var reg 4 % count_nxt [3:0] $end
$scope begin Combinational $end
$upscope $end
$scope begin FLOPS $end
$upscope $end
$upscope $end
$upscope $end
$enddefinitions $end
$comment Show the parameter values. $end
$dumpall
$end
#0
$dumpvars
bx %
bx $
1#
0"
bx !
$end
#5000
b1 %
b0 !
b0 $
1"
#10000
0"
#12000
0#
#15000
b10 %
b1 !
b1 $
1"
#20000
0"
#25000
b11 %
b10 !
b10 $
1"
#30000
0"
#35000
b100 %
b11 !
b11 $
1"
#40000
0"
#45000
b101 %
b100 !
b100 $
1"
#50000
0"
#55000
b110 %
b101 !
b101 $
1"
#60000
0"
#65000
b111 %
b110 !
b110 $
1"
